{"siteName":"Crowdpurr","logoUrl":"https://cdn.prod.website-files.com/5fdabf3c8ce5fe1f04b8745d/logo.png","themeColor":"#00A9E0","hero":{"title":"Welcome to Crowdpurr","subtitle":"Ready to check it out?","ctaText":"Get started right now with our free plan, no payment required.","imageUrl":"https://cdn.prod.website-files.com/5fdabf3c8ce5fe1f04b8745d/hero-image.jpg"},"features":[{"title":"Create, Configure and Run Your Event","description":"Create, configure and run your interactive event from anywhere using the web-based dashboard."},{"title":"Playback Options","description":"Manually control every step of your event. Or allow participants to interact at their own pace."},{"title":"Analyze Results","description":"Review all participant responses and rankings then export your entire event to a spreadsheet."}],"secondarySection":{"title":"Book a Free Demo","description":"Want to discuss it? Book a free demo to review your specific use-case.","imageUrl":"https://cdn.prod.website-files.com/5fdabf3c8ce5fe1f04b8745d/demo-image.jpg"},"contact":{"email":"support@crowdpurr.com","address":"123 Crowdpurr Lane, Austin, TX 73301"},"footer":"Crowdpurr – Fun and engaging interactive event experiences.","copyright":"© 2025 Crowdpurr. All rights reserved."}